pydanticai_platform_client/__init__.py
pydanticai_platform_client/client.py
pydanticai_platform_client/exceptions.py
pydanticai_platform_client/models.py
pydanticai_platform_client-0.1.0.dist-info/METADATA
pydanticai_platform_client-0.1.0.dist-info/WHEEL
pydanticai_platform_client-0.1.0.dist-info/RECORD
