Metadata-Version: 2.4
Name: pydanticai-platform-client
Version: 0.1.0
Summary: Client SDK for the PydanticAI Multi-Agent Platform
Author-email: bch <pbsd2008@gmail.com>
License-Expression: MIT
Classifier: Development Status :: 4 - Beta
Classifier: Intended Audience :: Developers
Classifier: License :: OSI Approved :: MIT License
Classifier: Programming Language :: Python :: 3
Classifier: Programming Language :: Python :: 3.10
Classifier: Programming Language :: Python :: 3.11
Classifier: Programming Language :: Python :: 3.12
Classifier: Typing :: Typed
Requires-Python: >=3.10
Requires-Dist: httpx>=0.25.0
Provides-Extra: dev
Requires-Dist: pytest-asyncio>=0.21; extra == 'dev'
Requires-Dist: pytest-httpx>=0.21; extra == 'dev'
Requires-Dist: pytest>=7.0; extra == 'dev'
